minos/transactions/__init__.py
minos/transactions/contextvars.py
minos/transactions/entries.py
minos/transactions/exceptions.py
minos/transactions/mixins.py
minos/transactions/repositories/__init__.py
minos/transactions/repositories/abc.py
minos/transactions/repositories/database/__init__.py
minos/transactions/repositories/database/factories.py
minos/transactions/repositories/database/impl.py
minos/transactions/repositories/memory.py
minos/transactions/testing/__init__.py
minos/transactions/testing/repositories/__init__.py
minos/transactions/testing/repositories/factories.py
minos/transactions/testing/repositories/testcases.py
minos_microservice_transactions-0.0.0.dist-info/LICENSE
minos_microservice_transactions-0.0.0.dist-info/WHEEL
minos_microservice_transactions-0.0.0.dist-info/METADATA
minos_microservice_transactions-0.0.0.dist-info/RECORD
