Metadata-Version: 2.1
Name: minos-microservice-transactions
Version: 0.0.0
Summary: The transactions core of the Minos Framework
Home-page: https://www.minos.run
License: MIT
Keywords: clariteia,minos,microservice,saga
Author: Minos Framework Devs
Author-email: hey@minos.run
Requires-Python: >=3.9,<4.0
Classifier: Development Status :: 4 - Beta
Classifier: Intended Audience :: Developers
Classifier: License :: OSI Approved :: MIT License
Classifier: Natural Language :: English
Classifier: Programming Language :: Python :: 3
Classifier: Programming Language :: Python :: 3.10
Classifier: Programming Language :: Python :: 3.9
Requires-Dist: cached-property (>=1.5.2,<2.0.0)
Requires-Dist: minos-microservice-common
Project-URL: Repository, https://github.com/minos-framework/minos-python
